electropy/__init__.py
electropy/charge.py
electropy/particle.py
tests/__init__.py
tests/test_charge.py
tests/test_particle.py
electropy-0.1.dev0.dist-info/LICENSE
electropy-0.1.dev0.dist-info/METADATA
electropy-0.1.dev0.dist-info/WHEEL
electropy-0.1.dev0.dist-info/top_level.txt
electropy-0.1.dev0.dist-info/RECORD
