Metadata-Version: 2.1
Name: electropy
Version: 0.1.dev0
Summary: Python tool for electromagnetism simulations
Home-page: https://github.com/electropy/electopy
Author: Mathieu Boudreau, PhD
Author-email: mathieu.boudreau2@mail.mcgill.ca
License: MIT
Platform: UNKNOWN
Classifier: Development Status :: 3 - Alpha
Classifier: License :: OSI Approved :: MIT License
Classifier: Programming Language :: Python :: 3.6
Requires-Dist: numpy (==1.16.2)
Requires-Dist: scipy (==1.2.1)
Requires-Dist: coverage (==4.4)
Requires-Dist: pytest (==3.6.0)
Requires-Dist: pytest-cov (==2.5.1)
